envencrypt_core/__init__.py
envencrypt_core/py.typed
envencrypt_core-0.1.2.dist-info/licenses/LICENSE
envencrypt_core-0.1.2.dist-info/WHEEL
envencrypt_core-0.1.2.dist-info/METADATA
envencrypt_core-0.1.2.dist-info/RECORD
