Metadata-Version: 2.4
Name: envencrypt-core
Version: 0.1.2
Summary: Core encryption utilities for python envencrypt
Author: Dyve, Igor Petrovic
Author-email: Dyve <dev@dyve.ch>, Igor Petrovic <758832+igorovic@users.noreply.github.com>
License-Expression: GPL-3.0-or-later
License-File: LICENSE
Requires-Dist: envencrypt-core-dpapi ; sys_platform == 'win32'
Requires-Python: >=3.11
